LICENSE.txt
MANIFEST.in
README.md
setup.cfg
setup.py
cloudspot/__init__.py
cloudspot/api.py
cloudspot/authhandler.py
cloudspot/config.py
cloudspot/constants/errors.py
cloudspot/constants/responses.py
cloudspot/endpoints/__init__.py
cloudspot/endpoints/artikels.py
cloudspot/endpoints/auth.py
cloudspot/endpoints/base.py
cloudspot/endpoints/categorieen.py
cloudspot/endpoints/klanten.py
cloudspot/models/__init__.py
cloudspot/models/artikels.py
cloudspot/models/auth.py
cloudspot/models/base.py
cloudspot/models/errors.py
cloudspot/models/klanten.py
cloudspot_erp_api.egg-info/PKG-INFO
cloudspot_erp_api.egg-info/SOURCES.txt
cloudspot_erp_api.egg-info/dependency_links.txt
cloudspot_erp_api.egg-info/requires.txt
cloudspot_erp_api.egg-info/top_level.txt