Metadata-Version: 2.1
Name: cloudspot-erp-api
Version: 1.0.0
Summary: Wrapper for the Cloudspot ERP API endpoints
Home-page: https://github.com/Ecosy-EU/inktool-wrapper
Download-URL: https://github.com/Ecosy-EU/cloudspot-api/archive/refs/tags/1.0.0.tar.gz
Author: Alexander Schillemans
Author-email: alexander.schillemans@lhs.global
License: GPL-3.0-or-later
Keywords: cloudspot
Classifier: Development Status :: 3 - Alpha
Classifier: Intended Audience :: Developers
Classifier: Topic :: Software Development :: Build Tools
Classifier: License :: OSI Approved :: GNU General Public License v3 or later (GPLv3+)
Classifier: Programming Language :: Python :: 3.6
License-File: LICENSE.txt
